dearpygui/__init__.py
dearpygui/_dearpygui.pyd
dearpygui/_dearpygui.pyi
dearpygui/dearpygui.py
dearpygui/demo.py
dearpygui/experimental.py
dearpygui/vcruntime140_1.dll
dearpyguiupdated-1.11.2.dist-info/LICENSE
dearpyguiupdated-1.11.2.dist-info/METADATA
dearpyguiupdated-1.11.2.dist-info/WHEEL
dearpyguiupdated-1.11.2.dist-info/top_level.txt
dearpyguiupdated-1.11.2.dist-info/RECORD
